AUTHORS
CHANGELOG.md
LICENSE
MANIFEST.in
README.md
setup.cfg
setup.py
versioneer.py
src/libreflow/__init__.py
src/libreflow/_version.py
src/libreflow/cli.py
src/libreflow/gui.py
src/libreflow/index.py
src/libreflow/jobs_cleaner.py
src/libreflow/jobs_node.py
src/libreflow/session.py
src/libreflow/sync.py
src/libreflow/sync_jobs_cleaner.py
src/libreflow.egg-info/PKG-INFO
src/libreflow.egg-info/SOURCES.txt
src/libreflow.egg-info/dependency_links.txt
src/libreflow.egg-info/requires.txt
src/libreflow.egg-info/top_level.txt
src/libreflow/baseflow/__init__.py
src/libreflow/baseflow/asset.py
src/libreflow/baseflow/departments.py
src/libreflow/baseflow/dependency.py
src/libreflow/baseflow/entity_manager.py
src/libreflow/baseflow/file.py
src/libreflow/baseflow/film.py
src/libreflow/baseflow/kitsu.py
src/libreflow/baseflow/lib.py
src/libreflow/baseflow/maputils.py
src/libreflow/baseflow/mytasks.py
src/libreflow/baseflow/runactions.py
src/libreflow/baseflow/runners.py
src/libreflow/baseflow/search.py
src/libreflow/baseflow/shot.py
src/libreflow/baseflow/site.py
src/libreflow/baseflow/task.py
src/libreflow/baseflow/task_manager.py
src/libreflow/baseflow/users.py
src/libreflow/baseflow/ui/__init__.py
src/libreflow/baseflow/ui/controller.py
src/libreflow/baseflow/ui/delegate.py
src/libreflow/baseflow/ui/file.py
src/libreflow/baseflow/ui/file_cell.py
src/libreflow/baseflow/ui/file_history.py
src/libreflow/baseflow/ui/file_list.py
src/libreflow/baseflow/ui/homepage.py
src/libreflow/baseflow/ui/job_queue.py
src/libreflow/baseflow/ui/qmodel.py
src/libreflow/baseflow/ui/task.py
src/libreflow/baseflow/ui/importfiles/__init__.py
src/libreflow/baseflow/ui/importfiles/custom_widget.py
src/libreflow/baseflow/ui/importfiles/files_list.py
src/libreflow/baseflow/ui/importfiles/target_wizard.py
src/libreflow/baseflow/ui/mytasks/__init__.py
src/libreflow/baseflow/ui/mytasks/components.py
src/libreflow/baseflow/ui/mytasks/edit_dialog.py
src/libreflow/baseflow/ui/mytasks/file_list.py
src/libreflow/baseflow/ui/mytasks/mytasks.py
src/libreflow/baseflow/ui/mytasks/qmodel.py
src/libreflow/custom_home/__init__.py
src/libreflow/custom_home/ui.py
src/libreflow/custom_home/wizard.py
