Metadata-Version: 2.4
Name: libreflow
Version: 2.12.7
Summary: An example flow for kabaret
Home-page: https://gitlab.com/lfs.coop/libreflow
Author: Flavio Perez
Author-email: flavio@lfs.coop
License: LGPLv3+
Keywords: kabaret cgwire kitsu gazu animation pipeline libreflow
Classifier: Programming Language :: Python :: 3
Classifier: Intended Audience :: Developers
Classifier: License :: OSI Approved :: GNU Lesser General Public License v3 or later (LGPLv3+)
Classifier: Operating System :: OS Independent
Requires-Python: >=3.7
License-File: LICENSE
License-File: AUTHORS
Requires-Dist: kabaret>=2.4.0rc6
Requires-Dist: pyside6
Requires-Dist: six~=1.0
Requires-Dist: kabaret.script-view>=1.3.1
Requires-Dist: kabaret.subprocess-manager>=1.3.1
Requires-Dist: kabaret.flow-contextual-dict>=0.3.0
Requires-Dist: kabaret.flow-entities
Requires-Dist: gazu>=0.8.33
Requires-Dist: minio
Requires-Dist: timeago
Requires-Dist: blender-asset-tracer
Requires-Dist: psutil
Requires-Dist: fileseq
Requires-Dist: sentry-sdk
Dynamic: author
Dynamic: author-email
Dynamic: classifier
Dynamic: description
Dynamic: description-content-type
Dynamic: home-page
Dynamic: keywords
Dynamic: license
Dynamic: license-file
Dynamic: requires-dist
Dynamic: requires-python
Dynamic: summary
